README.rst
setup.cfg
setup.py
pyteos_air/__init__.py
pyteos_air.egg-info/PKG-INFO
pyteos_air.egg-info/SOURCES.txt
pyteos_air.egg-info/dependency_links.txt
pyteos_air.egg-info/not-zip-safe
pyteos_air.egg-info/requires.txt
pyteos_air.egg-info/top_level.txt
pyteos_air/liq_ice_air/__init__.py
pyteos_air/liq_ice_air/liq_ice_air_f2py.F90
pyteos_air/liq_ice_air/g/__init__.py
pyteos_air/liq_ice_air/g_ref/__init__.py
pyteos_air/liq_ice_air/h/__init__.py
pyteos_air/liq_ice_air/il/__init__.py
pyteos_air/liq_ice_air/sat/__init__.py
pyteos_air/pyteos_interface/__init__.py
pyteos_air/pyteos_interface/create_gridded_data.py
pyteos_air/pyteos_interface/pyteos_interface.py
pyteos_air/teos_air/__init__.py
src/SIA_library/Air_1.F90
src/SIA_library/Air_2.F90
src/SIA_library/Air_3a.F90
src/SIA_library/Air_3b.F90
src/SIA_library/Air_3c.F90
src/SIA_library/Air_5.F90
src/SIA_library/Constants_0.F90
src/SIA_library/Convert_0.F90
src/SIA_library/Convert_5.F90
src/SIA_library/Flu_1.F90
src/SIA_library/Flu_2.F90
src/SIA_library/Flu_3a.F90
src/SIA_library/Flu_3b.F90
src/SIA_library/Flu_IF97_5.F90
src/SIA_library/GSW_Library_5.F90
src/SIA_library/Ice_1.F90
src/SIA_library/Ice_2.F90
src/SIA_library/Ice_Air_4a.F90
src/SIA_library/Ice_Air_4b.F90
src/SIA_library/Ice_Air_4c.F90
src/SIA_library/Ice_Air_4d.F90
src/SIA_library/Ice_Flu_5.F90
src/SIA_library/Ice_Liq_4.F90
src/SIA_library/Ice_Vap_4.F90
src/SIA_library/Liq_Air_4a.F90
src/SIA_library/Liq_Air_4b.F90
src/SIA_library/Liq_Air_4c.F90
src/SIA_library/Liq_Air_4d.F90
src/SIA_library/Liq_F03_5.F90
src/SIA_library/Liq_Ice_Air_4.F90
src/SIA_library/Liq_Ice_Air_5a.F90
src/SIA_library/Liq_Ice_Air_5b.F90
src/SIA_library/Liq_Ice_Air_5c.F90
src/SIA_library/Liq_Ice_Air_5d.F90
src/SIA_library/Liq_Vap_4.F90
src/SIA_library/Maths_0.F90
src/SIA_library/OS2008_5.F90
src/SIA_library/Sal_1.F90
src/SIA_library/Sal_2.F90
src/SIA_library/Sea_3a.F90
src/SIA_library/Sea_3b.F90
src/SIA_library/Sea_3c.F90
src/SIA_library/Sea_3d.F90
src/SIA_library/Sea_5a.F90
src/SIA_library/Sea_Air_4.F90
src/SIA_library/Sea_Ice_4.F90
src/SIA_library/Sea_Ice_Vap_4.F90
src/SIA_library/Sea_Liq_4.F90
src/SIA_library/Sea_Vap_4.F90