Metadata-Version: 1.1
Name: pyteos-air
Version: 1.0.2
Summary: This package provides python bindings to the atmospheric component of TEOS-10.                    Also includes expanded metorological quantities like the equivalent potential temperature.
Home-page: UNKNOWN
Author: F. Laliberte, R. Feistel, D. G. Wright, D. R. Jackett, K. Miyagawa, J. H. Reissmann, W. Wagner, U. Overhoff, C. Guder, A. Feistel, G. M. Marion
Author-email: frederic.laliberte@utoronto.ca
License: BSD
Keywords: thermodynamics atmosphere climate
Platform: UNKNOWN
Classifier: Development Status :: 4 - Beta
Classifier: Intended Audience :: Science/Research
Classifier: Natural Language :: English
Classifier: License :: OSI Approved :: BSD License
Classifier: Programming Language :: Python :: 2.7
Classifier: Programming Language :: Python :: 3.4
Classifier: Programming Language :: Python :: 3.5
Classifier: Programming Language :: Python :: 3.6
Classifier: Programming Language :: Fortran
Classifier: Topic :: Scientific/Engineering :: Atmospheric Science
Classifier: Topic :: Scientific/Engineering :: Mathematics
